pyanimeinfo/__init__.py
pyanimeinfo/bangumitv/__init__.py
pyanimeinfo/bangumitv/client.py
pyanimeinfo/bangumitv/enums.py
pyanimeinfo/bangumitv/exceptions.py
pyanimeinfo/config/__init__.py
pyanimeinfo/config/meta.py
pyanimeinfo/myanimelist/__init__.py
pyanimeinfo/myanimelist/jikanv4.py
pyanimeinfo/utils/__init__.py
pyanimeinfo/utils/download.py
pyanimeinfo/utils/enum.py
pyanimeinfo/utils/session.py
pyanimeinfo/utils/tqdm_.py
pyanimeinfo-0.0.3.dist-info/LICENSE
pyanimeinfo-0.0.3.dist-info/METADATA
pyanimeinfo-0.0.3.dist-info/WHEEL
pyanimeinfo-0.0.3.dist-info/top_level.txt
pyanimeinfo-0.0.3.dist-info/RECORD
