Metadata-Version: 2.1
Name: pyanimeinfo
Version: 0.0.3
Summary: Python anime information grabber.
Home-page: https://github.com/deepghs/pyanimeinfo
Author: narugo1992
Author-email: narugo992@gmail.com
License: Apache License, Version 2.0
Keywords: Python anime information grabber.
Classifier: Development Status :: 5 - Production/Stable
Classifier: Intended Audience :: Developers
Classifier: License :: OSI Approved :: Apache Software License
Classifier: Programming Language :: Python
Classifier: Programming Language :: Python :: 3
Classifier: Programming Language :: Python :: 3.8
Classifier: Programming Language :: Python :: 3.9
Classifier: Programming Language :: Python :: 3.10
Classifier: Programming Language :: Python :: 3.11
Classifier: Programming Language :: Python :: 3.12
Requires-Python: >=3.8
License-File: LICENSE
Requires-Dist: hbutils >=0.9.3
Requires-Dist: requests
Requires-Dist: tqdm
Requires-Dist: pyrfc6266
Requires-Dist: pyquery
Requires-Dist: lxml <5
Provides-Extra: doc
Requires-Dist: Jinja2 >=3.0.0 ; extra == 'doc'
Requires-Dist: sphinx >=3.2.0 ; extra == 'doc'
Requires-Dist: sphinx-rtd-theme >=0.4.3 ; extra == 'doc'
Requires-Dist: enum-tools >=0.9.0 ; extra == 'doc'
Requires-Dist: sphinx-toolbox ; extra == 'doc'
Requires-Dist: plantumlcli >=0.0.2 ; extra == 'doc'
Requires-Dist: packaging ; extra == 'doc'
Requires-Dist: sphinx-multiversion >=0.2.4 ; extra == 'doc'
Requires-Dist: where >=1.0.2 ; extra == 'doc'
Requires-Dist: easydict <2,>=1.7 ; extra == 'doc'
Requires-Dist: responses >=0.20.0 ; extra == 'doc'
Requires-Dist: matplotlib ; extra == 'doc'
Requires-Dist: natsort ; extra == 'doc'
Requires-Dist: nbsphinx >=0.8.8 ; extra == 'doc'
Requires-Dist: ipython >=7.16.3 ; extra == 'doc'
Requires-Dist: psutil >=5.8.0 ; extra == 'doc'
Requires-Dist: ipykernel >=6.15 ; extra == 'doc'
Requires-Dist: py-cpuinfo >=8.0.0 ; extra == 'doc'
Requires-Dist: click >=7.0.0 ; extra == 'doc'
Provides-Extra: tools
Requires-Dist: click >=8.0.0 ; extra == 'tools'
